README.md
package_info.json
setup.py
th2_grpc_sense/__init__.py
th2_grpc_sense/py.typed
th2_grpc_sense/sense.proto
th2_grpc_sense/sense_pb2.py
th2_grpc_sense/sense_pb2.pyi
th2_grpc_sense/sense_pb2_grpc.py
th2_grpc_sense/sense_service.py
th2_grpc_sense.egg-info/PKG-INFO
th2_grpc_sense.egg-info/SOURCES.txt
th2_grpc_sense.egg-info/dependency_links.txt
th2_grpc_sense.egg-info/requires.txt
th2_grpc_sense.egg-info/top_level.txt