Metadata-Version: 2.1
Name: th2-grpc-sense
Version: 0.0.1.dev4176782781
Summary: th2_grpc_sense
Home-page: https://github.com/th2-net/th2-sense
Author: TH2-devs
Author-email: th2-devs@exactprosystems.com
License: Apache License 2.0
Platform: UNKNOWN
Requires-Python: >=3.7
